Utila/__init__.py
Utila/utila.py
Utila-0.0.5.dist-info/DESCRIPTION.rst
Utila-0.0.5.dist-info/METADATA
Utila-0.0.5.dist-info/RECORD
Utila-0.0.5.dist-info/WHEEL
Utila-0.0.5.dist-info/metadata.json
Utila-0.0.5.dist-info/top_level.txt
