Metadata-Version: 2.0
Name: Utila
Version: 0.0.5
Summary: You need this
Home-page: https://github.com/AaIiMm/Utila
Author: Aime Risson
Author-email: aime.risson.1@gmail.com
License: UNKNOWN
Platform: UNKNOWN
Classifier: Programming Language :: Python
Classifier: Development Status :: 1 - Planning
Classifier: License :: OSI Approved
Classifier: Natural Language :: French
Classifier: Operating System :: OS Independent
Classifier: Programming Language :: Python :: 3
Classifier: Topic :: Communications
